nGR_waveforms_based_on_bilby/.DS_Store
nGR_waveforms_based_on_bilby/__init__.py
nGR_waveforms_based_on_bilby/source.py
ngr_waveforms_based_on_bilby-0.0.3.dist-info/METADATA
ngr_waveforms_based_on_bilby-0.0.3.dist-info/WHEEL
ngr_waveforms_based_on_bilby-0.0.3.dist-info/licenses/LICENSE
ngr_waveforms_based_on_bilby-0.0.3.dist-info/RECORD
