Metadata-Version: 2.1
Name: nGR_waveforms_based_on_bilby
Version: 0.0.3
Summary: nGR waveform package based on bilby.gw.source
Project-URL: Homepage, https://github.com/pypa/sampleproject
Project-URL: Bug Tracker, https://github.com/pypa/sampleproject/issues
Author-email: Yi Gong <gongyi@whu.edu.cn>
License-File: LICENSE
Classifier: License :: OSI Approved :: MIT License
Classifier: Operating System :: OS Independent
Classifier: Programming Language :: Python :: 3
Requires-Python: >=3.7
